chat.py
chat_interface.py
configure.py
list_models.py
main.py
token_streamer.py
openrouter_cli-0.1.4.dist-info/licenses/LICENSE
openrouter_cli-0.1.4.dist-info/METADATA
openrouter_cli-0.1.4.dist-info/WHEEL
openrouter_cli-0.1.4.dist-info/entry_points.txt
openrouter_cli-0.1.4.dist-info/top_level.txt
openrouter_cli-0.1.4.dist-info/RECORD
