Metadata-Version: 2.4
Name: openrouter-cli
Version: 0.1.4
Summary: Ollama-like CLI tool for openrouter
Requires-Python: >=3.12
License-File: LICENSE
Requires-Dist: humanize>=4.12.3
Requires-Dist: prompt-toolkit>=3.0.51
Requires-Dist: questionary>=2.1.0
Requires-Dist: requests>=2.32.3
Requires-Dist: rich>=14.0.0
Dynamic: license-file
